LICENSE
MANIFEST.in
README.rst
setup.py
absoluteurl/__init__.py
absoluteurl/templatetags/.DS_Store
absoluteurl/templatetags/__init__.py
absoluteurl/templatetags/absoluteurl.py
absoluteurl/templatetags/__pycache__/__init__.cpython-33.pyc
absoluteurl/templatetags/__pycache__/absoluteurl.cpython-33.pyc
django_absoluteurl.egg-info/PKG-INFO
django_absoluteurl.egg-info/SOURCES.txt
django_absoluteurl.egg-info/dependency_links.txt
django_absoluteurl.egg-info/top_level.txt