Metadata-Version: 1.1
Name: django-absoluteurl
Version: 1.0
Summary: Absolute Url is an app for creating absolute urls in Django templates.
Home-page: https://github.com/bgryszko/django-absoluteurl
Author: Bartosz Gryszko
Author-email: b@gryszko.com
License: MIT
Platform: UNKNOWN
Classifier: Environment :: Web Environment
Classifier: Framework :: Django
Classifier: Intended Audience :: Developers
Classifier: License :: OSI Approved :: MIT License
Classifier: Operating System :: OS Independent
Classifier: Programming Language :: Python
Classifier: Programming Language :: Python :: 2.6
Classifier: Programming Language :: Python :: 2.7
Classifier: Programming Language :: Python :: 3
Classifier: Topic :: Internet :: WWW/HTTP
Classifier: Topic :: Internet :: WWW/HTTP :: Dynamic Content
